autobisect/__init__.py
autobisect/__main__.py
autobisect/args.py
autobisect/bisect.py
autobisect/build_manager.py
autobisect/builds.py
autobisect/config.py
autobisect/evaluators/__init__.py
autobisect/evaluators/base.py
autobisect/evaluators/browser/__init__.py
autobisect/evaluators/browser/args.py
autobisect/evaluators/browser/browser.py
autobisect/evaluators/js/__init__.py
autobisect/evaluators/js/args.py
autobisect/evaluators/js/js.py
autobisect/main.py
autobisect-9.0.0.dist-info/METADATA
autobisect-9.0.0.dist-info/WHEEL
autobisect-9.0.0.dist-info/entry_points.txt
autobisect-9.0.0.dist-info/licenses/LICENSE
autobisect-9.0.0.dist-info/RECORD
