Metadata-Version: 2.4
Name: autobisect
Version: 9.0.0
Summary: Automatic bisection utility for Mozilla Firefox and SpiderMonkey
License-Expression: MPL-2.0
License-File: LICENSE
Keywords: bisection,fuzz,fuzzing,security,test,testing
Author: Jason Kratzer
Author-email: jkratzer@mozilla.com
Maintainer: Mozilla Fuzzing Team
Maintainer-email: fuzzing@mozilla.com
Requires-Python: >=3.10,<4.0
Classifier: Intended Audience :: Developers
Classifier: License :: OSI Approved :: Mozilla Public License 2.0 (MPL 2.0)
Classifier: Programming Language :: Python :: 3
Classifier: Topic :: Security
Classifier: Topic :: Software Development :: Testing
Requires-Dist: fuzzfetch (>=16.1.0,<17.0.0)
Requires-Dist: grizzly-framework (>=0.24.0,<0.25.0)
Requires-Dist: lithium-reducer (>=4.0.0,<5.0.0)
Requires-Dist: platformdirs (>=4.2.2,<5.0.0)
Requires-Dist: twine (>=6.1.0,<7.0.0)
